<?xml version="1.0" ?>
<palette name="PANTONE+ Pastels &amp; Neons Uncoated" fixedID="32" guid="cd6f12ce-e9f6-4167-b12a-e6606c992be7" prefix="PANTONE " locked="true">
 <colorspaces>
  <cs name="PANTONE Yellow 0131 U" fixedID="1" version="1500">
   <color cs="LAB" tints="0.9559,0.475882352941176,0.672862745098039"/>
   <color cs="sRGB" tints="0.984313725490196,0.96078431372549,0.607843137254902"/>
   <color cs="AdobeRGB" tints="0.976470588235294,0.96078431372549,0.623529411764706"/>
  </cs>
  <cs name="PANTONE Red 0331 U" fixedID="2" version="1500">
   <color cs="LAB" tints="0.8115,0.632941176470588,0.530235294117647"/>
   <color cs="sRGB" tints="1,0.694117647058824,0.745098039215686"/>
   <color cs="AdobeRGB" tints="0.941176470588235,0.686274509803922,0.737254901960784"/>
  </cs>
  <cs name="PANTONE Magenta 0521 U" fixedID="3" version="1500">
   <color cs="LAB" tints="0.7894,0.643529411764706,0.452549019607843"/>
   <color cs="sRGB" tints="0.972549019607843,0.666666666666667,0.866666666666667"/>
   <color cs="AdobeRGB" tints="0.898039215686275,0.658823529411765,0.854901960784314"/>
  </cs>
  <cs name="PANTONE Violet 0631 U" fixedID="4" version="1500">
   <color cs="LAB" tints="0.6708,0.602901960784314,0.374980392156863"/>
   <color cs="sRGB" tints="0.729411764705882,0.576470588235294,0.874509803921569"/>
   <color cs="AdobeRGB" tints="0.682352941176471,0.572549019607843,0.858823529411765"/>
  </cs>
  <cs name="PANTONE Blue 0821 U" fixedID="5" version="1500">
   <color cs="LAB" tints="0.7823,0.404196078431373,0.403058823529412"/>
   <color cs="sRGB" tints="0.423529411764706,0.819607843137255,0.937254901960784"/>
   <color cs="AdobeRGB" tints="0.568627450980392,0.815686274509804,0.929411764705882"/>
  </cs>
  <cs name="PANTONE Green 0921 U" fixedID="6" version="1500">
   <color cs="LAB" tints="0.8391,0.353921568627451,0.497490196078431"/>
   <color cs="sRGB" tints="0.470588235294118,0.901960784313726,0.815686274509804"/>
   <color cs="AdobeRGB" tints="0.627450980392157,0.901960784313726,0.815686274509804"/>
  </cs>
  <cs name="PANTONE Black 0961 U" fixedID="7" version="1500">
   <color cs="LAB" tints="0.6348,0.506823529411765,0.513529411764706"/>
   <color cs="sRGB" tints="0.615686274509804,0.6,0.580392156862745"/>
   <color cs="AdobeRGB" tints="0.607843137254902,0.592156862745098,0.576470588235294"/>
  </cs>
  <cs name="PANTONE 9140 U" fixedID="8" version="1500">
   <color cs="LAB" tints="0.9508,0.494470588235294,0.598156862745098"/>
   <color cs="sRGB" tints="0.980392156862745,0.945098039215686,0.752941176470588"/>
   <color cs="AdobeRGB" tints="0.968627450980392,0.945098039215686,0.756862745098039"/>
  </cs>
  <cs name="PANTONE 9284 U" fixedID="127" version="1500">
   <color cs="LAB" tints="0.882,0.579490196078431,0.514235294117647"/>
   <color cs="sRGB" tints="1,0.811764705882353,0.847058823529412"/>
   <color cs="AdobeRGB" tints="0.956862745098039,0.807843137254902,0.843137254901961"/>
  </cs>
  <cs name="PANTONE 9324 U" fixedID="128" version="1500">
   <color cs="LAB" tints="0.8682,0.585137254901961,0.470588235294118"/>
   <color cs="sRGB" tints="0.980392156862745,0.796078431372549,0.913725490196078"/>
   <color cs="AdobeRGB" tints="0.929411764705882,0.792156862745098,0.905882352941176"/>
  </cs>
  <cs name="PANTONE 9344 U" fixedID="129" version="1500">
   <color cs="LAB" tints="0.7924,0.57156862745098,0.421137254901961"/>
   <color cs="sRGB" tints="0.83921568627451,0.729411764705882,0.92156862745098"/>
   <color cs="AdobeRGB" tints="0.803921568627451,0.72156862745098,0.913725490196078"/>
  </cs>
  <cs name="PANTONE 9464 U" fixedID="130" version="1500">
   <color cs="LAB" tints="0.8304,0.419490196078431,0.426313725490196"/>
   <color cs="sRGB" tints="0.56078431372549,0.862745098039216,0.945098039215686"/>
   <color cs="AdobeRGB" tints="0.658823529411765,0.858823529411765,0.941176470588235"/>
  </cs>
  <cs name="PANTONE 9524 U" fixedID="131" version="1500">
   <color cs="LAB" tints="0.8834,0.397647058823529,0.497490196078431"/>
   <color cs="sRGB" tints="0.643137254901961,0.929411764705882,0.866666666666667"/>
   <color cs="AdobeRGB" tints="0.733333333333333,0.929411764705882,0.866666666666667"/>
  </cs>
  <cs name="PANTONE 9084 U" fixedID="132" version="1500">
   <color cs="LAB" tints="0.7484,0.507333333333333,0.517372549019608"/>
   <color cs="sRGB" tints="0.741176470588235,0.717647058823529,0.694117647058824"/>
   <color cs="AdobeRGB" tints="0.729411764705882,0.713725490196078,0.690196078431373"/>
  </cs>
  <cs name="PANTONE 9060 U" fixedID="17" version="1500">
   <color cs="LAB" tints="0.9632,0.492705882352941,0.562117647058824"/>
   <color cs="sRGB" tints="0.972549019607843,0.964705882352941,0.83921568627451"/>
   <color cs="AdobeRGB" tints="0.968627450980392,0.96078431372549,0.83921568627451"/>
  </cs>
  <cs name="PANTONE 9280 U" fixedID="57" version="1500">
   <color cs="LAB" tints="0.9308,0.538156862745098,0.512745098039216"/>
   <color cs="sRGB" tints="0.992156862745098,0.898039215686275,0.901960784313726"/>
   <color cs="AdobeRGB" tints="0.964705882352941,0.894117647058824,0.898039215686275"/>
  </cs>
  <cs name="PANTONE 9320 U" fixedID="66" version="1500">
   <color cs="LAB" tints="0.9164,0.547686274509804,0.48756862745098"/>
   <color cs="sRGB" tints="0.980392156862745,0.87843137254902,0.933333333333333"/>
   <color cs="AdobeRGB" tints="0.949019607843137,0.874509803921569,0.929411764705882"/>
  </cs>
  <cs name="PANTONE 9340 U" fixedID="71" version="1500">
   <color cs="LAB" tints="0.925,0.523960784313726,0.485294117647059"/>
   <color cs="sRGB" tints="0.945098039215686,0.901960784313726,0.945098039215686"/>
   <color cs="AdobeRGB" tints="0.929411764705882,0.898039215686275,0.945098039215686"/>
  </cs>
  <cs name="PANTONE 9460 U" fixedID="92" version="1500">
   <color cs="LAB" tints="0.8997,0.454,0.466117647058824"/>
   <color cs="sRGB" tints="0.76078431372549,0.917647058823529,0.952941176470588"/>
   <color cs="AdobeRGB" tints="0.807843137254902,0.917647058823529,0.949019607843137"/>
  </cs>
  <cs name="PANTONE 9520 U" fixedID="107" version="1500">
   <color cs="LAB" tints="0.9196,0.435372549019608,0.501686274509804"/>
   <color cs="sRGB" tints="0.772549019607843,0.949019607843137,0.901960784313726"/>
   <color cs="AdobeRGB" tints="0.823529411764706,0.949019607843137,0.901960784313726"/>
  </cs>
  <cs name="PANTONE 9083 U" fixedID="28" version="1500">
   <color cs="LAB" tints="0.7761,0.506901960784314,0.517843137254902"/>
   <color cs="sRGB" tints="0.768627450980392,0.749019607843137,0.72156862745098"/>
   <color cs="AdobeRGB" tints="0.756862745098039,0.745098039215686,0.717647058823529"/>
  </cs>
  <cs name="PANTONE 9064 U" fixedID="133" version="1500">
   <color cs="LAB" tints="0.9639,0.493137254901961,0.55964705882353"/>
   <color cs="sRGB" tints="0.972549019607843,0.964705882352941,0.843137254901961"/>
   <color cs="AdobeRGB" tints="0.968627450980392,0.96078431372549,0.843137254901961"/>
  </cs>
  <cs name="PANTONE 9285 U" fixedID="134" version="1500">
   <color cs="LAB" tints="0.9512,0.517490196078431,0.515333333333333"/>
   <color cs="sRGB" tints="0.980392156862745,0.933333333333333,0.917647058823529"/>
   <color cs="AdobeRGB" tints="0.968627450980392,0.933333333333333,0.917647058823529"/>
  </cs>
  <cs name="PANTONE 9061 U" fixedID="18" version="1500">
   <color cs="LAB" tints="0.9447,0.525058823529412,0.502549019607843"/>
   <color cs="sRGB" tints="0.980392156862745,0.92156862745098,0.937254901960784"/>
   <color cs="AdobeRGB" tints="0.96078431372549,0.92156862745098,0.933333333333333"/>
  </cs>
  <cs name="PANTONE 9345 U" fixedID="135" version="1500">
   <color cs="LAB" tints="0.9368,0.516941176470588,0.498705882352941"/>
   <color cs="sRGB" tints="0.952941176470588,0.92156862745098,0.933333333333333"/>
   <color cs="AdobeRGB" tints="0.941176470588235,0.917647058823529,0.929411764705882"/>
  </cs>
  <cs name="PANTONE 9062 U" fixedID="19" version="1500">
   <color cs="LAB" tints="0.9379,0.480039215686275,0.495529411764706"/>
   <color cs="sRGB" tints="0.882352941176471,0.945098039215686,0.937254901960784"/>
   <color cs="AdobeRGB" tints="0.898039215686275,0.945098039215686,0.937254901960784"/>
  </cs>
  <cs name="PANTONE 9063 U" fixedID="20" version="1500">
   <color cs="LAB" tints="0.946,0.475725490196078,0.512980392156863"/>
   <color cs="sRGB" tints="0.894117647058824,0.956862745098039,0.913725490196078"/>
   <color cs="AdobeRGB" tints="0.909803921568627,0.952941176470588,0.913725490196078"/>
  </cs>
  <cs name="PANTONE 9081 U" fixedID="24" version="1500">
   <color cs="LAB" tints="0.8615,0.505725490196078,0.51921568627451"/>
   <color cs="sRGB" tints="0.862745098039216,0.843137254901961,0.811764705882353"/>
   <color cs="AdobeRGB" tints="0.850980392156863,0.83921568627451,0.807843137254902"/>
  </cs>
  <cs name="PANTONE 9043 U" fixedID="16" version="1500">
   <color cs="LAB" tints="0.9143,0.504627450980392,0.519764705882353"/>
   <color cs="sRGB" tints="0.917647058823529,0.901960784313726,0.866666666666667"/>
   <color cs="AdobeRGB" tints="0.909803921568627,0.898039215686275,0.866666666666667"/>
  </cs>
  <cs name="PANTONE 9080 U" fixedID="21" version="1500">
   <color cs="LAB" tints="0.8764,0.505490196078431,0.519058823529412"/>
   <color cs="sRGB" tints="0.87843137254902,0.858823529411765,0.827450980392157"/>
   <color cs="AdobeRGB" tints="0.866666666666667,0.854901960784314,0.823529411764706"/>
  </cs>
  <cs name="PANTONE 9100 U" fixedID="22" version="1500">
   <color cs="LAB" tints="0.9189,0.500627450980392,0.517058823529412"/>
   <color cs="sRGB" tints="0.913725490196078,0.909803921568627,0.87843137254902"/>
   <color cs="AdobeRGB" tints="0.909803921568627,0.905882352941176,0.874509803921569"/>
  </cs>
  <cs name="PANTONE 9101 U" fixedID="23" version="1500">
   <color cs="LAB" tints="0.8847,0.497843137254902,0.514470588235294"/>
   <color cs="sRGB" tints="0.870588235294118,0.874509803921569,0.843137254901961"/>
   <color cs="AdobeRGB" tints="0.866666666666667,0.870588235294118,0.843137254901961"/>
  </cs>
  <cs name="PANTONE 9102 U" fixedID="25" version="1500">
   <color cs="LAB" tints="0.8407,0.495725490196078,0.511176470588235"/>
   <color cs="sRGB" tints="0.815686274509804,0.827450980392157,0.803921568627451"/>
   <color cs="AdobeRGB" tints="0.811764705882353,0.823529411764706,0.8"/>
  </cs>
  <cs name="PANTONE 9103 U" fixedID="26" version="1500">
   <color cs="LAB" tints="0.7993,0.49443137254902,0.508235294117647"/>
   <color cs="sRGB" tints="0.764705882352941,0.780392156862745,0.764705882352941"/>
   <color cs="AdobeRGB" tints="0.764705882352941,0.776470588235294,0.76078431372549"/>
  </cs>
  <cs name="PANTONE 9082 U" fixedID="27" version="1500">
   <color cs="LAB" tints="0.8216,0.506392156862745,0.519647058823529"/>
   <color cs="sRGB" tints="0.819607843137255,0.8,0.768627450980392"/>
   <color cs="AdobeRGB" tints="0.807843137254902,0.792156862745098,0.764705882352941"/>
  </cs>
  <cs name="PANTONE 9121 U" fixedID="33" version="1500">
   <color cs="LAB" tints="0.9595,0.481803921568627,0.621921568627451"/>
   <color cs="sRGB" tints="0.976470588235294,0.964705882352941,0.713725490196078"/>
   <color cs="AdobeRGB" tints="0.972549019607843,0.964705882352941,0.72156862745098"/>
  </cs>
  <cs name="PANTONE 9120 U" fixedID="32" version="1500">
   <color cs="LAB" tints="0.9602,0.484,0.60921568627451"/>
   <color cs="sRGB" tints="0.976470588235294,0.964705882352941,0.741176470588235"/>
   <color cs="AdobeRGB" tints="0.972549019607843,0.964705882352941,0.745098039215686"/>
  </cs>
  <cs name="PANTONE 9141 U" fixedID="29" version="1500">
   <color cs="LAB" tints="0.9502,0.493686274509804,0.60956862745098"/>
   <color cs="sRGB" tints="0.980392156862745,0.945098039215686,0.729411764705882"/>
   <color cs="AdobeRGB" tints="0.972549019607843,0.945098039215686,0.737254901960784"/>
  </cs>
  <cs name="PANTONE 9142 U" fixedID="30" version="1500">
   <color cs="LAB" tints="0.8945,0.500313725490196,0.581647058823529"/>
   <color cs="sRGB" tints="0.917647058823529,0.882352941176471,0.725490196078431"/>
   <color cs="AdobeRGB" tints="0.905882352941176,0.87843137254902,0.729411764705882"/>
  </cs>
  <cs name="PANTONE 9161 U" fixedID="40" version="1500">
   <color cs="LAB" tints="0.878,0.511725490196078,0.580078431372549"/>
   <color cs="sRGB" tints="0.92156862745098,0.854901960784314,0.713725490196078"/>
   <color cs="AdobeRGB" tints="0.898039215686275,0.850980392156863,0.713725490196078"/>
  </cs>
  <cs name="PANTONE 9143 U" fixedID="31" version="1500">
   <color cs="LAB" tints="0.8781,0.498078431372549,0.565254901960784"/>
   <color cs="sRGB" tints="0.890196078431373,0.862745098039216,0.741176470588235"/>
   <color cs="AdobeRGB" tints="0.87843137254902,0.858823529411765,0.741176470588235"/>
  </cs>
  <cs name="PANTONE 9162 U" fixedID="41" version="1500">
   <color cs="LAB" tints="0.843,0.511411764705882,0.561176470588235"/>
   <color cs="sRGB" tints="0.870588235294118,0.815686274509804,0.709803921568627"/>
   <color cs="AdobeRGB" tints="0.850980392156863,0.811764705882353,0.709803921568627"/>
  </cs>
  <cs name="PANTONE 9160 U" fixedID="39" version="1500">
   <color cs="LAB" tints="0.9252,0.518274509803922,0.595098039215686"/>
   <color cs="sRGB" tints="0.992156862745098,0.901960784313726,0.733333333333333"/>
   <color cs="AdobeRGB" tints="0.964705882352941,0.898039215686275,0.737254901960784"/>
  </cs>
  <cs name="PANTONE 9180 U" fixedID="36" version="1500">
   <color cs="LAB" tints="0.9333,0.519960784313726,0.562156862745098"/>
   <color cs="sRGB" tints="0.988235294117647,0.909803921568627,0.807843137254902"/>
   <color cs="AdobeRGB" tints="0.964705882352941,0.909803921568627,0.807843137254902"/>
  </cs>
  <cs name="PANTONE 9181 U" fixedID="37" version="1500">
   <color cs="LAB" tints="0.9176,0.529294117647059,0.576588235294118"/>
   <color cs="sRGB" tints="0.992156862745098,0.886274509803922,0.76078431372549"/>
   <color cs="AdobeRGB" tints="0.964705882352941,0.882352941176471,0.764705882352941"/>
  </cs>
  <cs name="PANTONE 9200 U" fixedID="43" version="1500">
   <color cs="LAB" tints="0.9091,0.538705882352941,0.569411764705882"/>
   <color cs="sRGB" tints="0.996078431372549,0.870588235294118,0.768627450980392"/>
   <color cs="AdobeRGB" tints="0.96078431372549,0.866666666666667,0.768627450980392"/>
  </cs>
  <cs name="PANTONE 9201 U" fixedID="44" version="1500">
   <color cs="LAB" tints="0.9189,0.531960784313726,0.56756862745098"/>
   <color cs="sRGB" tints="0.996078431372549,0.886274509803922,0.780392156862745"/>
   <color cs="AdobeRGB" tints="0.964705882352941,0.882352941176471,0.780392156862745"/>
  </cs>
  <cs name="PANTONE 9220 U" fixedID="45" version="1500">
   <color cs="LAB" tints="0.9146,0.538117647058823,0.555960784313726"/>
   <color cs="sRGB" tints="0.996078431372549,0.87843137254902,0.8"/>
   <color cs="AdobeRGB" tints="0.964705882352941,0.874509803921569,0.8"/>
  </cs>
  <cs name="PANTONE 9221 U" fixedID="46" version="1500">
   <color cs="LAB" tints="0.8741,0.537137254901961,0.551882352941176"/>
   <color cs="sRGB" tints="0.945098039215686,0.835294117647059,0.764705882352941"/>
   <color cs="AdobeRGB" tints="0.913725490196078,0.831372549019608,0.76078431372549"/>
  </cs>
  <cs name="PANTONE 9184 U" fixedID="136" version="1500">
   <color cs="LAB" tints="0.9372,0.50956862745098,0.544117647058823"/>
   <color cs="sRGB" tints="0.964705882352941,0.92156862745098,0.847058823529412"/>
   <color cs="AdobeRGB" tints="0.952941176470588,0.92156862745098,0.847058823529412"/>
  </cs>
  <cs name="PANTONE 9185 U" fixedID="137" version="1500">
   <color cs="LAB" tints="0.913,0.516941176470588,0.546470588235294"/>
   <color cs="sRGB" tints="0.952941176470588,0.890196078431373,0.815686274509804"/>
   <color cs="AdobeRGB" tints="0.933333333333333,0.890196078431373,0.815686274509804"/>
  </cs>
  <cs name="PANTONE 9202 U" fixedID="48" version="1500">
   <color cs="LAB" tints="0.8843,0.527019607843137,0.552588235294118"/>
   <color cs="sRGB" tints="0.941176470588235,0.850980392156863,0.772549019607843"/>
   <color cs="AdobeRGB" tints="0.913725490196078,0.847058823529412,0.772549019607843"/>
  </cs>
  <cs name="PANTONE 9182 U" fixedID="38" version="1500">
   <color cs="LAB" tints="0.8828,0.525176470588235,0.55756862745098"/>
   <color cs="sRGB" tints="0.937254901960784,0.850980392156863,0.76078431372549"/>
   <color cs="AdobeRGB" tints="0.913725490196078,0.847058823529412,0.76078431372549"/>
  </cs>
  <cs name="PANTONE 9183 U" fixedID="47" version="1500">
   <color cs="LAB" tints="0.8685,0.520549019607843,0.546078431372549"/>
   <color cs="sRGB" tints="0.909803921568627,0.83921568627451,0.768627450980392"/>
   <color cs="AdobeRGB" tints="0.886274509803922,0.835294117647059,0.764705882352941"/>
  </cs>
  <cs name="PANTONE 9203 U" fixedID="49" version="1500">
   <color cs="LAB" tints="0.8404,0.524862745098039,0.548549019607843"/>
   <color cs="sRGB" tints="0.886274509803922,0.807843137254902,0.733333333333333"/>
   <color cs="AdobeRGB" tints="0.858823529411765,0.8,0.729411764705882"/>
  </cs>
  <cs name="PANTONE 9186 U" fixedID="138" version="1500">
   <color cs="LAB" tints="0.8425,0.522509803921569,0.54321568627451"/>
   <color cs="sRGB" tints="0.882352941176471,0.811764705882353,0.745098039215686"/>
   <color cs="AdobeRGB" tints="0.858823529411765,0.803921568627451,0.741176470588235"/>
  </cs>
  <cs name="PANTONE 9224 U" fixedID="139" version="1500">
   <color cs="LAB" tints="0.9398,0.515921568627451,0.541647058823529"/>
   <color cs="sRGB" tints="0.980392156862745,0.92156862745098,0.854901960784314"/>
   <color cs="AdobeRGB" tints="0.96078431372549,0.92156862745098,0.850980392156863"/>
  </cs>
  <cs name="PANTONE 9225 U" fixedID="140" version="1500">
   <color cs="LAB" tints="0.9209,0.519803921568628,0.544156862745098"/>
   <color cs="sRGB" tints="0.964705882352941,0.898039215686275,0.827450980392157"/>
   <color cs="AdobeRGB" tints="0.945098039215686,0.894117647058824,0.827450980392157"/>
  </cs>
  <cs name="PANTONE 9226 U" fixedID="141" version="1500">
   <color cs="LAB" tints="0.9135,0.513490196078431,0.533176470588235"/>
   <color cs="sRGB" tints="0.941176470588235,0.894117647058824,0.843137254901961"/>
   <color cs="AdobeRGB" tints="0.925490196078431,0.890196078431373,0.83921568627451"/>
  </cs>
  <cs name="PANTONE 9222 U" fixedID="54" version="1500">
   <color cs="LAB" tints="0.8478,0.529725490196079,0.542470588235294"/>
   <color cs="sRGB" tints="0.898039215686275,0.811764705882353,0.752941176470588"/>
   <color cs="AdobeRGB" tints="0.870588235294118,0.807843137254902,0.749019607843137"/>
  </cs>
  <cs name="PANTONE 9223 U" fixedID="55" version="1500">
   <color cs="LAB" tints="0.8266,0.525098039215686,0.538666666666667"/>
   <color cs="sRGB" tints="0.866666666666667,0.792156862745098,0.737254901960784"/>
   <color cs="AdobeRGB" tints="0.843137254901961,0.784313725490196,0.733333333333333"/>
  </cs>
  <cs name="PANTONE 9242 U" fixedID="53" version="1500">
   <color cs="LAB" tints="0.8532,0.539490196078431,0.532666666666667"/>
   <color cs="sRGB" tints="0.917647058823529,0.811764705882353,0.776470588235294"/>
   <color cs="AdobeRGB" tints="0.886274509803922,0.803921568627451,0.772549019607843"/>
  </cs>
  <cs name="PANTONE 9243 U" fixedID="56" version="1500">
   <color cs="LAB" tints="0.8212,0.534941176470588,0.529450980392157"/>
   <color cs="sRGB" tints="0.874509803921569,0.780392156862745,0.749019607843137"/>
   <color cs="AdobeRGB" tints="0.843137254901961,0.772549019607843,0.745098039215686"/>
  </cs>
  <cs name="PANTONE 9244 U" fixedID="142" version="1500">
   <color cs="LAB" tints="0.943,0.522705882352941,0.526745098039216"/>
   <color cs="sRGB" tints="0.988235294117647,0.92156862745098,0.886274509803922"/>
   <color cs="AdobeRGB" tints="0.968627450980392,0.917647058823529,0.886274509803922"/>
  </cs>
  <cs name="PANTONE 9240 U" fixedID="50" version="1500">
   <color cs="LAB" tints="0.9305,0.532313725490196,0.529019607843137"/>
   <color cs="sRGB" tints="0.992156862745098,0.901960784313726,0.870588235294118"/>
   <color cs="AdobeRGB" tints="0.964705882352941,0.898039215686275,0.866666666666667"/>
  </cs>
  <cs name="PANTONE 9260 U" fixedID="52" version="1500">
   <color cs="LAB" tints="0.9207,0.541647058823529,0.523058823529412"/>
   <color cs="sRGB" tints="0.992156862745098,0.882352941176471,0.870588235294118"/>
   <color cs="AdobeRGB" tints="0.96078431372549,0.882352941176471,0.866666666666667"/>
  </cs>
  <cs name="PANTONE 9241 U" fixedID="51" version="1500">
   <color cs="LAB" tints="0.8917,0.53843137254902,0.531098039215686"/>
   <color cs="sRGB" tints="0.956862745098039,0.854901960784314,0.823529411764706"/>
   <color cs="AdobeRGB" tints="0.929411764705882,0.850980392156863,0.819607843137255"/>
  </cs>
  <cs name="PANTONE 9261 U" fixedID="61" version="1500">
   <color cs="LAB" tints="0.8688,0.552,0.526470588235294"/>
   <color cs="sRGB" tints="0.952941176470588,0.819607843137255,0.807843137254902"/>
   <color cs="AdobeRGB" tints="0.917647058823529,0.815686274509804,0.803921568627451"/>
  </cs>
  <cs name="PANTONE 9262 U" fixedID="62" version="1500">
   <color cs="LAB" tints="0.8425,0.547882352941176,0.527254901960784"/>
   <color cs="sRGB" tints="0.917647058823529,0.792156862745098,0.776470588235294"/>
   <color cs="AdobeRGB" tints="0.882352941176471,0.788235294117647,0.772549019607843"/>
  </cs>
  <cs name="PANTONE 9263 U" fixedID="63" version="1500">
   <color cs="LAB" tints="0.8122,0.54121568627451,0.525607843137255"/>
   <color cs="sRGB" tints="0.870588235294118,0.764705882352941,0.749019607843137"/>
   <color cs="AdobeRGB" tints="0.83921568627451,0.76078431372549,0.741176470588235"/>
  </cs>
  <cs name="PANTONE 9286 U" fixedID="143" version="1500">
   <color cs="LAB" tints="0.9155,0.549686274509804,0.51243137254902"/>
   <color cs="sRGB" tints="0.996078431372549,0.874509803921569,0.886274509803922"/>
   <color cs="AdobeRGB" tints="0.96078431372549,0.870588235294118,0.882352941176471"/>
  </cs>
  <cs name="PANTONE 9281 U" fixedID="58" version="1500">
   <color cs="LAB" tints="0.8893,0.552235294117647,0.512470588235294"/>
   <color cs="sRGB" tints="0.972549019607843,0.843137254901961,0.858823529411765"/>
   <color cs="AdobeRGB" tints="0.933333333333333,0.83921568627451,0.850980392156863"/>
  </cs>
  <cs name="PANTONE 9300 U" fixedID="64" version="1500">
   <color cs="LAB" tints="0.92,0.543843137254902,0.500666666666667"/>
   <color cs="sRGB" tints="0.984313725490196,0.882352941176471,0.913725490196078"/>
   <color cs="AdobeRGB" tints="0.956862745098039,0.87843137254902,0.909803921568627"/>
  </cs>
  <cs name="PANTONE 9282 U" fixedID="59" version="1500">
   <color cs="LAB" tints="0.8581,0.555098039215686,0.513647058823529"/>
   <color cs="sRGB" tints="0.941176470588235,0.803921568627451,0.819607843137255"/>
   <color cs="AdobeRGB" tints="0.901960784313726,0.8,0.815686274509804"/>
  </cs>
  <cs name="PANTONE 9301 U" fixedID="65" version="1500">
   <color cs="LAB" tints="0.8926,0.549490196078431,0.500862745098039"/>
   <color cs="sRGB" tints="0.964705882352941,0.847058823529412,0.882352941176471"/>
   <color cs="AdobeRGB" tints="0.929411764705882,0.843137254901961,0.87843137254902"/>
  </cs>
  <cs name="PANTONE 9321 U" fixedID="69" version="1500">
   <color cs="LAB" tints="0.8963,0.548117647058824,0.48843137254902"/>
   <color cs="sRGB" tints="0.956862745098039,0.854901960784314,0.909803921568627"/>
   <color cs="AdobeRGB" tints="0.925490196078431,0.850980392156863,0.905882352941176"/>
  </cs>
  <cs name="PANTONE 9302 U" fixedID="67" version="1500">
   <color cs="LAB" tints="0.8359,0.561333333333333,0.501882352941176"/>
   <color cs="sRGB" tints="0.917647058823529,0.776470588235294,0.819607843137255"/>
   <color cs="AdobeRGB" tints="0.87843137254902,0.772549019607843,0.811764705882353"/>
  </cs>
  <cs name="PANTONE 9021 U" fixedID="10" version="1500">
   <color cs="LAB" tints="0.9274,0.52556862745098,0.515725490196078"/>
   <color cs="sRGB" tints="0.968627450980392,0.901960784313726,0.890196078431373"/>
   <color cs="AdobeRGB" tints="0.949019607843137,0.898039215686275,0.890196078431373"/>
  </cs>
  <cs name="PANTONE 9022 U" fixedID="11" version="1500">
   <color cs="LAB" tints="0.9238,0.52921568627451,0.499490196078431"/>
   <color cs="sRGB" tints="0.96078431372549,0.898039215686275,0.917647058823529"/>
   <color cs="AdobeRGB" tints="0.941176470588235,0.894117647058824,0.913725490196078"/>
  </cs>
  <cs name="PANTONE 9023 U" fixedID="12" version="1500">
   <color cs="LAB" tints="0.9151,0.523098039215686,0.486627450980392"/>
   <color cs="sRGB" tints="0.933333333333333,0.894117647058824,0.933333333333333"/>
   <color cs="AdobeRGB" tints="0.917647058823529,0.890196078431373,0.929411764705882"/>
  </cs>
  <cs name="PANTONE 9283 U" fixedID="60" version="1500">
   <color cs="LAB" tints="0.8363,0.543960784313726,0.517725490196079"/>
   <color cs="sRGB" tints="0.898039215686275,0.788235294117647,0.788235294117647"/>
   <color cs="AdobeRGB" tints="0.866666666666667,0.784313725490196,0.784313725490196"/>
  </cs>
  <cs name="PANTONE 9303 U" fixedID="68" version="1500">
   <color cs="LAB" tints="0.8013,0.557019607843137,0.502313725490196"/>
   <color cs="sRGB" tints="0.874509803921569,0.745098039215686,0.780392156862745"/>
   <color cs="AdobeRGB" tints="0.835294117647059,0.737254901960784,0.772549019607843"/>
  </cs>
  <cs name="PANTONE 9322 U" fixedID="70" version="1500">
   <color cs="LAB" tints="0.8531,0.559764705882353,0.48643137254902"/>
   <color cs="sRGB" tints="0.925490196078431,0.8,0.866666666666667"/>
   <color cs="AdobeRGB" tints="0.890196078431373,0.792156862745098,0.858823529411765"/>
  </cs>
  <cs name="PANTONE 9323 U" fixedID="77" version="1500">
   <color cs="LAB" tints="0.8012,0.556862745098039,0.490509803921569"/>
   <color cs="sRGB" tints="0.866666666666667,0.745098039215686,0.8"/>
   <color cs="AdobeRGB" tints="0.831372549019608,0.737254901960784,0.796078431372549"/>
  </cs>
  <cs name="PANTONE 9360 U" fixedID="75" version="1500">
   <color cs="LAB" tints="0.8732,0.528470588235294,0.456823529411765"/>
   <color cs="sRGB" tints="0.874509803921569,0.843137254901961,0.941176470588235"/>
   <color cs="AdobeRGB" tints="0.862745098039216,0.83921568627451,0.937254901960784"/>
  </cs>
  <cs name="PANTONE 9341 U" fixedID="72" version="1500">
   <color cs="LAB" tints="0.8784,0.535098039215686,0.472705882352941"/>
   <color cs="sRGB" tints="0.905882352941176,0.843137254901961,0.917647058823529"/>
   <color cs="AdobeRGB" tints="0.886274509803922,0.83921568627451,0.913725490196078"/>
  </cs>
  <cs name="PANTONE 9342 U" fixedID="73" version="1500">
   <color cs="LAB" tints="0.8652,0.533058823529412,0.476980392156863"/>
   <color cs="sRGB" tints="0.890196078431373,0.831372549019608,0.898039215686275"/>
   <color cs="AdobeRGB" tints="0.870588235294118,0.827450980392157,0.890196078431373"/>
  </cs>
  <cs name="PANTONE 9343 U" fixedID="74" version="1500">
   <color cs="LAB" tints="0.8396,0.53956862745098,0.468509803921569"/>
   <color cs="sRGB" tints="0.866666666666667,0.8,0.882352941176471"/>
   <color cs="AdobeRGB" tints="0.843137254901961,0.792156862745098,0.87843137254902"/>
  </cs>
  <cs name="PANTONE 9361 U" fixedID="76" version="1500">
   <color cs="LAB" tints="0.8405,0.536156862745098,0.453019607843137"/>
   <color cs="sRGB" tints="0.850980392156863,0.803921568627451,0.913725490196078"/>
   <color cs="AdobeRGB" tints="0.835294117647059,0.8,0.905882352941176"/>
  </cs>
  <cs name="PANTONE 9362 U" fixedID="83" version="1500">
   <color cs="LAB" tints="0.809,0.538352941176471,0.451960784313725"/>
   <color cs="sRGB" tints="0.819607843137255,0.768627450980392,0.882352941176471"/>
   <color cs="AdobeRGB" tints="0.8,0.76078431372549,0.874509803921569"/>
  </cs>
  <cs name="PANTONE 9363 U" fixedID="84" version="1500">
   <color cs="LAB" tints="0.7923,0.535725490196079,0.458901960784314"/>
   <color cs="sRGB" tints="0.8,0.749019607843137,0.850980392156863"/>
   <color cs="AdobeRGB" tints="0.780392156862745,0.745098039215686,0.843137254901961"/>
  </cs>
  <cs name="PANTONE 9380 U" fixedID="79" version="1500">
   <color cs="LAB" tints="0.8766,0.510078431372549,0.455960784313726"/>
   <color cs="sRGB" tints="0.843137254901961,0.858823529411765,0.949019607843137"/>
   <color cs="AdobeRGB" tints="0.843137254901961,0.854901960784314,0.941176470588235"/>
  </cs>
  <cs name="PANTONE 9384 U" fixedID="144" version="1500">
   <color cs="LAB" tints="0.8784,0.504862745098039,0.458627450980392"/>
   <color cs="sRGB" tints="0.83921568627451,0.866666666666667,0.945098039215686"/>
   <color cs="AdobeRGB" tints="0.843137254901961,0.862745098039216,0.937254901960784"/>
  </cs>
  <cs name="PANTONE 9381 U" fixedID="80" version="1500">
   <color cs="LAB" tints="0.8402,0.50443137254902,0.451333333333333"/>
   <color cs="sRGB" tints="0.788235294117647,0.823529411764706,0.913725490196078"/>
   <color cs="AdobeRGB" tints="0.796078431372549,0.819607843137255,0.909803921568627"/>
  </cs>
  <cs name="PANTONE 9382 U" fixedID="81" version="1500">
   <color cs="LAB" tints="0.8214,0.510823529411765,0.444196078431373"/>
   <color cs="sRGB" tints="0.776470588235294,0.8,0.905882352941176"/>
   <color cs="AdobeRGB" tints="0.776470588235294,0.796078431372549,0.901960784313726"/>
  </cs>
  <cs name="PANTONE 9383 U" fixedID="82" version="1500">
   <color cs="LAB" tints="0.8002,0.510313725490196,0.451372549019608"/>
   <color cs="sRGB" tints="0.756862745098039,0.776470588235294,0.870588235294118"/>
   <color cs="AdobeRGB" tints="0.756862745098039,0.772549019607843,0.862745098039216"/>
  </cs>
  <cs name="PANTONE 9385 U" fixedID="145" version="1500">
   <color cs="LAB" tints="0.8403,0.498941176470588,0.468745098039216"/>
   <color cs="sRGB" tints="0.792156862745098,0.827450980392157,0.882352941176471"/>
   <color cs="AdobeRGB" tints="0.796078431372549,0.823529411764706,0.874509803921569"/>
  </cs>
  <cs name="PANTONE 9403 U" fixedID="87" version="1500">
   <color cs="LAB" tints="0.8034,0.489372549019608,0.451490196078431"/>
   <color cs="sRGB" tints="0.72156862745098,0.792156862745098,0.874509803921569"/>
   <color cs="AdobeRGB" tints="0.737254901960784,0.788235294117647,0.866666666666667"/>
  </cs>
  <cs name="PANTONE 9400 U" fixedID="78" version="1500">
   <color cs="LAB" tints="0.9043,0.493098039215686,0.467254901960784"/>
   <color cs="sRGB" tints="0.850980392156863,0.901960784313726,0.956862745098039"/>
   <color cs="AdobeRGB" tints="0.858823529411765,0.898039215686275,0.952941176470588"/>
  </cs>
  <cs name="PANTONE 9401 U" fixedID="85" version="1500">
   <color cs="LAB" tints="0.8727,0.491019607843137,0.450039215686275"/>
   <color cs="sRGB" tints="0.796078431372549,0.866666666666667,0.952941176470588"/>
   <color cs="AdobeRGB" tints="0.811764705882353,0.862745098039216,0.949019607843137"/>
  </cs>
  <cs name="PANTONE 9402 U" fixedID="86" version="1500">
   <color cs="LAB" tints="0.8284,0.489764705882353,0.446392156862745"/>
   <color cs="sRGB" tints="0.745098039215686,0.819607843137255,0.909803921568627"/>
   <color cs="AdobeRGB" tints="0.76078431372549,0.815686274509804,0.905882352941176"/>
  </cs>
  <cs name="PANTONE 9420 U" fixedID="88" version="1500">
   <color cs="LAB" tints="0.8535,0.47521568627451,0.444901960784314"/>
   <color cs="sRGB" tints="0.737254901960784,0.854901960784314,0.941176470588235"/>
   <color cs="AdobeRGB" tints="0.768627450980392,0.850980392156863,0.933333333333333"/>
  </cs>
  <cs name="PANTONE 9421 U" fixedID="89" version="1500">
   <color cs="LAB" tints="0.8248,0.475294117647059,0.44556862745098"/>
   <color cs="sRGB" tints="0.709803921568627,0.823529411764706,0.905882352941176"/>
   <color cs="AdobeRGB" tints="0.737254901960784,0.819607843137255,0.901960784313726"/>
  </cs>
  <cs name="PANTONE 9422 U" fixedID="90" version="1500">
   <color cs="LAB" tints="0.8169,0.481372549019608,0.457607843137255"/>
   <color cs="sRGB" tints="0.72156862745098,0.811764705882353,0.874509803921569"/>
   <color cs="AdobeRGB" tints="0.745098039215686,0.807843137254902,0.870588235294118"/>
  </cs>
  <cs name="PANTONE 9423 U" fixedID="91" version="1500">
   <color cs="LAB" tints="0.7889,0.48156862745098,0.460980392156863"/>
   <color cs="sRGB" tints="0.694117647058824,0.780392156862745,0.83921568627451"/>
   <color cs="AdobeRGB" tints="0.717647058823529,0.776470588235294,0.831372549019608"/>
  </cs>
  <cs name="PANTONE 9424 U" fixedID="146" version="1500">
   <color cs="LAB" tints="0.8859,0.457254901960784,0.470980392156863"/>
   <color cs="sRGB" tints="0.756862745098039,0.901960784313726,0.925490196078431"/>
   <color cs="AdobeRGB" tints="0.796078431372549,0.898039215686275,0.92156862745098"/>
  </cs>
  <cs name="PANTONE 9440 U" fixedID="93" version="1500">
   <color cs="LAB" tints="0.8646,0.459725490196078,0.449137254901961"/>
   <color cs="sRGB" tints="0.72156862745098,0.87843137254902,0.945098039215686"/>
   <color cs="AdobeRGB" tints="0.764705882352941,0.874509803921569,0.941176470588235"/>
  </cs>
  <cs name="PANTONE 9441 U" fixedID="95" version="1500">
   <color cs="LAB" tints="0.8558,0.45521568627451,0.443176470588235"/>
   <color cs="sRGB" tints="0.694117647058824,0.870588235294118,0.945098039215686"/>
   <color cs="AdobeRGB" tints="0.745098039215686,0.866666666666667,0.941176470588235"/>
  </cs>
  <cs name="PANTONE 9442 U" fixedID="96" version="1500">
   <color cs="LAB" tints="0.8151,0.451764705882353,0.443960784313726"/>
   <color cs="sRGB" tints="0.643137254901961,0.827450980392157,0.898039215686275"/>
   <color cs="AdobeRGB" tints="0.698039215686274,0.823529411764706,0.890196078431373"/>
  </cs>
  <cs name="PANTONE 9461 U" fixedID="94" version="1500">
   <color cs="LAB" tints="0.8443,0.438039215686275,0.451019607843137"/>
   <color cs="sRGB" tints="0.650980392156863,0.866666666666667,0.917647058823529"/>
   <color cs="AdobeRGB" tints="0.717647058823529,0.862745098039216,0.913725490196078"/>
  </cs>
  <cs name="PANTONE 9462 U" fixedID="98" version="1500">
   <color cs="LAB" tints="0.8142,0.442313725490196,0.456274509803922"/>
   <color cs="sRGB" tints="0.635294117647059,0.831372549019608,0.874509803921569"/>
   <color cs="AdobeRGB" tints="0.690196078431373,0.827450980392157,0.866666666666667"/>
  </cs>
  <cs name="PANTONE 9443 U" fixedID="97" version="1500">
   <color cs="LAB" tints="0.7923,0.460980392156863,0.452666666666667"/>
   <color cs="sRGB" tints="0.650980392156863,0.796078431372549,0.858823529411765"/>
   <color cs="AdobeRGB" tints="0.690196078431373,0.792156862745098,0.850980392156863"/>
  </cs>
  <cs name="PANTONE 9480 U" fixedID="99" version="1500">
   <color cs="LAB" tints="0.9011,0.441607843137255,0.472705882352941"/>
   <color cs="sRGB" tints="0.741176470588235,0.929411764705882,0.937254901960784"/>
   <color cs="AdobeRGB" tints="0.796078431372549,0.925490196078431,0.937254901960784"/>
  </cs>
  <cs name="PANTONE 9481 U" fixedID="100" version="1500">
   <color cs="LAB" tints="0.8886,0.435333333333333,0.472509803921569"/>
   <color cs="sRGB" tints="0.713725490196078,0.917647058823529,0.925490196078431"/>
   <color cs="AdobeRGB" tints="0.772549019607843,0.913725490196078,0.92156862745098"/>
  </cs>
  <cs name="PANTONE 9500 U" fixedID="102" version="1500">
   <color cs="LAB" tints="0.8878,0.423294117647059,0.47678431372549"/>
   <color cs="sRGB" tints="0.690196078431373,0.92156862745098,0.913725490196078"/>
   <color cs="AdobeRGB" tints="0.76078431372549,0.92156862745098,0.913725490196078"/>
  </cs>
  <cs name="PANTONE 9482 U" fixedID="101" version="1500">
   <color cs="LAB" tints="0.853,0.436509803921569,0.47078431372549"/>
   <color cs="sRGB" tints="0.674509803921569,0.87843137254902,0.890196078431373"/>
   <color cs="AdobeRGB" tints="0.737254901960784,0.874509803921569,0.886274509803922"/>
  </cs>
  <cs name="PANTONE 9501 U" fixedID="103" version="1500">
   <color cs="LAB" tints="0.8444,0.430392156862745,0.480352941176471"/>
   <color cs="sRGB" tints="0.662745098039216,0.870588235294118,0.858823529411765"/>
   <color cs="AdobeRGB" tints="0.725490196078431,0.866666666666667,0.858823529411765"/>
  </cs>
  <cs name="PANTONE 9483 U" fixedID="104" version="1500">
   <color cs="LAB" tints="0.8206,0.458313725490196,0.486509803921569"/>
   <color cs="sRGB" tints="0.701960784313725,0.827450980392157,0.823529411764706"/>
   <color cs="AdobeRGB" tints="0.737254901960784,0.823529411764706,0.819607843137255"/>
  </cs>
  <cs name="PANTONE 9463 U" fixedID="105" version="1500">
   <color cs="LAB" tints="0.8177,0.454941176470588,0.469411764705882"/>
   <color cs="sRGB" tints="0.67843137254902,0.827450980392157,0.854901960784314"/>
   <color cs="AdobeRGB" tints="0.717647058823529,0.823529411764706,0.847058823529412"/>
  </cs>
  <cs name="PANTONE 9042 U" fixedID="15" version="1500">
   <color cs="LAB" tints="0.9221,0.491294117647059,0.505450980392157"/>
   <color cs="sRGB" tints="0.894117647058824,0.917647058823529,0.901960784313726"/>
   <color cs="AdobeRGB" tints="0.898039215686275,0.917647058823529,0.901960784313726"/>
  </cs>
  <cs name="PANTONE 9041 U" fixedID="14" version="1500">
   <color cs="LAB" tints="0.9317,0.473137254901961,0.512470588235294"/>
   <color cs="sRGB" tints="0.874509803921569,0.941176470588235,0.898039215686275"/>
   <color cs="AdobeRGB" tints="0.890196078431373,0.941176470588235,0.898039215686275"/>
  </cs>
  <cs name="PANTONE 9040 U" fixedID="13" version="1500">
   <color cs="LAB" tints="0.9273,0.475450980392157,0.485843137254902"/>
   <color cs="sRGB" tints="0.854901960784314,0.937254901960784,0.945098039215686"/>
   <color cs="AdobeRGB" tints="0.874509803921569,0.933333333333333,0.945098039215686"/>
  </cs>
  <cs name="PANTONE 9044 U" fixedID="147" version="1500">
   <color cs="LAB" tints="0.8616,0.454352941176471,0.484117647058824"/>
   <color cs="sRGB" tints="0.737254901960784,0.874509803921569,0.874509803921569"/>
   <color cs="AdobeRGB" tints="0.772549019607843,0.870588235294118,0.870588235294118"/>
  </cs>
  <cs name="PANTONE 9045 U" fixedID="148" version="1500">
   <color cs="LAB" tints="0.84,0.457098039215686,0.492627450980392"/>
   <color cs="sRGB" tints="0.725490196078431,0.850980392156863,0.835294117647059"/>
   <color cs="AdobeRGB" tints="0.756862745098039,0.847058823529412,0.831372549019608"/>
  </cs>
  <cs name="PANTONE 9503 U" fixedID="112" version="1500">
   <color cs="LAB" tints="0.8192,0.45921568627451,0.494313725490196"/>
   <color cs="sRGB" tints="0.709803921568627,0.823529411764706,0.807843137254902"/>
   <color cs="AdobeRGB" tints="0.741176470588235,0.819607843137255,0.803921568627451"/>
  </cs>
  <cs name="PANTONE 9504 U" fixedID="149" version="1500">
   <color cs="LAB" tints="0.8156,0.461176470588235,0.491411764705882"/>
   <color cs="sRGB" tints="0.705882352941177,0.819607843137255,0.811764705882353"/>
   <color cs="AdobeRGB" tints="0.737254901960784,0.815686274509804,0.807843137254902"/>
  </cs>
  <cs name="PANTONE 9525 U" fixedID="150" version="1500">
   <color cs="LAB" tints="0.9514,0.470823529411765,0.527176470588235"/>
   <color cs="sRGB" tints="0.898039215686275,0.964705882352941,0.890196078431373"/>
   <color cs="AdobeRGB" tints="0.917647058823529,0.964705882352941,0.890196078431373"/>
  </cs>
  <cs name="PANTONE 9540 U" fixedID="113" version="1500">
   <color cs="LAB" tints="0.9341,0.450509803921569,0.520745098039216"/>
   <color cs="sRGB" tints="0.835294117647059,0.956862745098039,0.882352941176471"/>
   <color cs="AdobeRGB" tints="0.870588235294118,0.956862745098039,0.882352941176471"/>
  </cs>
  <cs name="PANTONE 9541 U" fixedID="106" version="1500">
   <color cs="LAB" tints="0.9129,0.456901960784314,0.519019607843137"/>
   <color cs="sRGB" tints="0.823529411764706,0.929411764705882,0.862745098039216"/>
   <color cs="AdobeRGB" tints="0.850980392156863,0.929411764705882,0.862745098039216"/>
  </cs>
  <cs name="PANTONE 9521 U" fixedID="108" version="1500">
   <color cs="LAB" tints="0.9031,0.455372549019608,0.504901960784314"/>
   <color cs="sRGB" tints="0.8,0.92156862745098,0.87843137254902"/>
   <color cs="AdobeRGB" tints="0.831372549019608,0.917647058823529,0.87843137254902"/>
  </cs>
  <cs name="PANTONE 9522 U" fixedID="109" version="1500">
   <color cs="LAB" tints="0.8694,0.457725490196078,0.505647058823529"/>
   <color cs="sRGB" tints="0.768627450980392,0.882352941176471,0.843137254901961"/>
   <color cs="AdobeRGB" tints="0.8,0.87843137254902,0.83921568627451"/>
  </cs>
  <cs name="PANTONE 9523 U" fixedID="110" version="1500">
   <color cs="LAB" tints="0.8592,0.470352941176471,0.507647058823529"/>
   <color cs="sRGB" tints="0.784313725490196,0.862745098039216,0.827450980392157"/>
   <color cs="AdobeRGB" tints="0.803921568627451,0.858823529411765,0.823529411764706"/>
  </cs>
  <cs name="PANTONE 9502 U" fixedID="111" version="1500">
   <color cs="LAB" tints="0.8395,0.449137254901961,0.489254901960784"/>
   <color cs="sRGB" tints="0.705882352941177,0.854901960784314,0.83921568627451"/>
   <color cs="AdobeRGB" tints="0.745098039215686,0.850980392156863,0.835294117647059"/>
  </cs>
  <cs name="PANTONE 9544 U" fixedID="151" version="1500">
   <color cs="LAB" tints="0.9562,0.479176470588235,0.535058823529412"/>
   <color cs="sRGB" tints="0.925490196078431,0.964705882352941,0.882352941176471"/>
   <color cs="AdobeRGB" tints="0.933333333333333,0.964705882352941,0.882352941176471"/>
  </cs>
  <cs name="PANTONE 9560 U" fixedID="114" version="1500">
   <color cs="LAB" tints="0.9462,0.461058823529412,0.535647058823529"/>
   <color cs="sRGB" tints="0.87843137254902,0.964705882352941,0.870588235294118"/>
   <color cs="AdobeRGB" tints="0.901960784313726,0.964705882352941,0.870588235294118"/>
  </cs>
  <cs name="PANTONE 9561 U" fixedID="115" version="1500">
   <color cs="LAB" tints="0.9067,0.459843137254902,0.538980392156863"/>
   <color cs="sRGB" tints="0.835294117647059,0.92156862745098,0.819607843137255"/>
   <color cs="AdobeRGB" tints="0.858823529411765,0.917647058823529,0.819607843137255"/>
  </cs>
  <cs name="PANTONE 9562 U" fixedID="116" version="1500">
   <color cs="LAB" tints="0.873,0.470039215686274,0.535411764705882"/>
   <color cs="sRGB" tints="0.815686274509804,0.87843137254902,0.788235294117647"/>
   <color cs="AdobeRGB" tints="0.831372549019608,0.874509803921569,0.788235294117647"/>
  </cs>
  <cs name="PANTONE 9563 U" fixedID="117" version="1500">
   <color cs="LAB" tints="0.8339,0.476627450980392,0.531647058823529"/>
   <color cs="sRGB" tints="0.784313725490196,0.831372549019608,0.756862745098039"/>
   <color cs="AdobeRGB" tints="0.792156862745098,0.823529411764706,0.752941176470588"/>
  </cs>
  <cs name="PANTONE 9542 U" fixedID="118" version="1500">
   <color cs="LAB" tints="0.8353,0.470509803921569,0.520313725490196"/>
   <color cs="sRGB" tints="0.768627450980392,0.835294117647059,0.776470588235294"/>
   <color cs="AdobeRGB" tints="0.784313725490196,0.831372549019608,0.776470588235294"/>
  </cs>
  <cs name="PANTONE 9543 U" fixedID="119" version="1500">
   <color cs="LAB" tints="0.806,0.465411764705882,0.521294117647059"/>
   <color cs="sRGB" tints="0.725490196078431,0.803921568627451,0.745098039215686"/>
   <color cs="AdobeRGB" tints="0.745098039215686,0.8,0.741176470588235"/>
  </cs>
  <cs name="PANTONE 9020 U" fixedID="9" version="1500">
   <color cs="LAB" tints="0.9458,0.485098039215686,0.602274509803922"/>
   <color cs="sRGB" tints="0.956862745098039,0.949019607843137,0.741176470588235"/>
   <color cs="AdobeRGB" tints="0.952941176470588,0.945098039215686,0.745098039215686"/>
  </cs>
  <cs name="PANTONE 9600 U" fixedID="120" version="1500">
   <color cs="LAB" tints="0.9427,0.475882352941176,0.579607843137255"/>
   <color cs="sRGB" tints="0.929411764705882,0.949019607843137,0.780392156862745"/>
   <color cs="AdobeRGB" tints="0.933333333333333,0.949019607843137,0.784313725490196"/>
  </cs>
  <cs name="PANTONE 9601 U" fixedID="152" version="1500">
   <color cs="LAB" tints="0.9223,0.484588235294118,0.562"/>
   <color cs="sRGB" tints="0.913725490196078,0.92156862745098,0.792156862745098"/>
   <color cs="AdobeRGB" tints="0.913725490196078,0.92156862745098,0.792156862745098"/>
  </cs>
  <cs name="PANTONE 9122 U" fixedID="34" version="1500">
   <color cs="LAB" tints="0.9009,0.489098039215686,0.591254901960784"/>
   <color cs="sRGB" tints="0.909803921568627,0.894117647058824,0.713725490196078"/>
   <color cs="AdobeRGB" tints="0.901960784313726,0.890196078431373,0.717647058823529"/>
  </cs>
  <cs name="PANTONE 9602 U" fixedID="124" version="1500">
   <color cs="LAB" tints="0.8679,0.486352941176471,0.564039215686275"/>
   <color cs="sRGB" tints="0.854901960784314,0.858823529411765,0.729411764705882"/>
   <color cs="AdobeRGB" tints="0.854901960784314,0.854901960784314,0.729411764705882"/>
  </cs>
  <cs name="PANTONE 9603 U" fixedID="125" version="1500">
   <color cs="LAB" tints="0.8281,0.491411764705882,0.551725490196078"/>
   <color cs="sRGB" tints="0.815686274509804,0.815686274509804,0.713725490196078"/>
   <color cs="AdobeRGB" tints="0.811764705882353,0.807843137254902,0.709803921568627"/>
  </cs>
  <cs name="PANTONE 9123 U" fixedID="35" version="1500">
   <color cs="LAB" tints="0.8316,0.494078431372549,0.575725490196078"/>
   <color cs="sRGB" tints="0.835294117647059,0.815686274509804,0.670588235294118"/>
   <color cs="AdobeRGB" tints="0.823529411764706,0.811764705882353,0.670588235294118"/>
  </cs>
  <cs name="PANTONE 9580 U" fixedID="121" version="1500">
   <color cs="LAB" tints="0.9481,0.468588235294118,0.562196078431373"/>
   <color cs="sRGB" tints="0.909803921568627,0.96078431372549,0.819607843137255"/>
   <color cs="AdobeRGB" tints="0.92156862745098,0.96078431372549,0.819607843137255"/>
  </cs>
  <cs name="PANTONE 9581 U" fixedID="122" version="1500">
   <color cs="LAB" tints="0.9088,0.472705882352941,0.555019607843137"/>
   <color cs="sRGB" tints="0.870588235294118,0.913725490196078,0.792156862745098"/>
   <color cs="AdobeRGB" tints="0.882352941176471,0.913725490196078,0.792156862745098"/>
  </cs>
  <cs name="PANTONE 9584 U" fixedID="153" version="1500">
   <color cs="LAB" tints="0.8886,0.481921568627451,0.545843137254902"/>
   <color cs="sRGB" tints="0.862745098039216,0.886274509803922,0.788235294117647"/>
   <color cs="AdobeRGB" tints="0.866666666666667,0.882352941176471,0.788235294117647"/>
  </cs>
  <cs name="PANTONE 9582 U" fixedID="123" version="1500">
   <color cs="LAB" tints="0.8551,0.486156862745098,0.540196078431373"/>
   <color cs="sRGB" tints="0.831372549019608,0.847058823529412,0.76078431372549"/>
   <color cs="AdobeRGB" tints="0.831372549019608,0.843137254901961,0.76078431372549"/>
  </cs>
  <cs name="PANTONE 9583 U" fixedID="126" version="1500">
   <color cs="LAB" tints="0.8336,0.485019607843137,0.542705882352941"/>
   <color cs="sRGB" tints="0.803921568627451,0.823529411764706,0.733333333333333"/>
   <color cs="AdobeRGB" tints="0.807843137254902,0.819607843137255,0.733333333333333"/>
  </cs>
  <cs name="PANTONE 9585 U" fixedID="154" version="1500">
   <color cs="LAB" tints="0.8534,0.485372549019608,0.541411764705882"/>
   <color cs="sRGB" tints="0.827450980392157,0.847058823529412,0.756862745098039"/>
   <color cs="AdobeRGB" tints="0.827450980392157,0.843137254901961,0.756862745098039"/>
  </cs>
  <cs name="PANTONE 9163 U" fixedID="42" version="1500">
   <color cs="LAB" tints="0.8302,0.508549019607843,0.548549019607843"/>
   <color cs="sRGB" tints="0.847058823529412,0.803921568627451,0.72156862745098"/>
   <color cs="AdobeRGB" tints="0.831372549019608,0.8,0.717647058823529"/>
  </cs>
  <cs name="PANTONE 801 U" fixedID="801" version="1500">
   <color cs="LAB" tints="0.574,0.385372549019608,0.346078431372549"/>
   <color cs="sRGB" tints="0,0.611764705882353,0.803921568627451"/>
   <color cs="AdobeRGB" tints="0.250980392156863,0.603921568627451,0.792156862745098"/>
  </cs>
  <cs name="PANTONE 802 U" fixedID="802" version="1500">
   <color cs="LAB" tints="0.7391,0.254901960784314,0.724862745098039"/>
   <color cs="sRGB" tints="0.231372549019608,0.823529411764706,0.23921568627451"/>
   <color cs="AdobeRGB" tints="0.498039215686275,0.819607843137255,0.301960784313725"/>
  </cs>
  <cs name="PANTONE 803 U" fixedID="803" version="1500">
   <color cs="LAB" tints="0.941,0.516039215686275,0.855450980392157"/>
   <color cs="sRGB" tints="1,0.913725490196078,0.0862745098039216"/>
   <color cs="AdobeRGB" tints="1,0.909803921568627,0.235294117647059"/>
  </cs>
  <cs name="PANTONE 804 U" fixedID="804" version="1500">
   <color cs="LAB" tints="0.8429,0.687411764705882,0.763803921568627"/>
   <color cs="sRGB" tints="1,0.666666666666667,0.32156862745098"/>
   <color cs="AdobeRGB" tints="1,0.662745098039216,0.345098039215686"/>
  </cs>
  <cs name="PANTONE 805 U" fixedID="805" version="1500">
   <color cs="LAB" tints="0.7391,0.774980392156863,0.645843137254902"/>
   <color cs="sRGB" tints="1,0.454901960784314,0.466666666666667"/>
   <color cs="AdobeRGB" tints="1,0.450980392156863,0.462745098039216"/>
  </cs>
  <cs name="PANTONE 806 U" fixedID="806" version="1500">
   <color cs="LAB" tints="0.6579,0.818313725490196,0.476196078431373"/>
   <color cs="sRGB" tints="1,0.282352941176471,0.690196078431373"/>
   <color cs="AdobeRGB" tints="0.933333333333333,0.290196078431373,0.674509803921569"/>
  </cs>
  <cs name="PANTONE 807 U" fixedID="807" version="1500">
   <color cs="LAB" tints="0.5717,0.797098039215686,0.389450980392157"/>
   <color cs="sRGB" tints="0.909803921568627,0.219607843137255,0.749019607843137"/>
   <color cs="AdobeRGB" tints="0.784313725490196,0.227450980392157,0.729411764705882"/>
  </cs>
  <cs name="PANTONE 901 U" fixedID="901" version="1500">
   <color cs="LAB" tints="0.6304,0.384078431372549,0.352"/>
   <color cs="sRGB" tints="0,0.670588235294118,0.854901960784314"/>
   <color cs="AdobeRGB" tints="0.32156862745098,0.666666666666667,0.847058823529412"/>
  </cs>
  <cs name="PANTONE 902 U" fixedID="902" version="1500">
   <color cs="LAB" tints="0.838,0.318117647058824,0.672392156862745"/>
   <color cs="sRGB" tints="0.529411764705882,0.909803921568627,0.470588235294118"/>
   <color cs="AdobeRGB" tints="0.662745098039216,0.909803921568627,0.498039215686275"/>
  </cs>
  <cs name="PANTONE 903 U" fixedID="903" version="1500">
   <color cs="LAB" tints="0.9579,0.487333333333333,0.768039215686275"/>
   <color cs="sRGB" tints="1,0.952941176470588,0.403921568627451"/>
   <color cs="AdobeRGB" tints="1,0.952941176470588,0.443137254901961"/>
  </cs>
  <cs name="PANTONE 904 U" fixedID="904" version="1500">
   <color cs="LAB" tints="0.8884,0.614509803921569,0.680627450980392"/>
   <color cs="sRGB" tints="1,0.788235294117647,0.533333333333333"/>
   <color cs="AdobeRGB" tints="1,0.780392156862745,0.541176470588235"/>
  </cs>
  <cs name="PANTONE 905 U" fixedID="905" version="1500">
   <color cs="LAB" tints="0.7942,0.69678431372549,0.573764705882353"/>
   <color cs="sRGB" tints="1,0.615686274509804,0.647058823529412"/>
   <color cs="AdobeRGB" tints="1,0.607843137254902,0.63921568627451"/>
  </cs>
  <cs name="PANTONE 906 U" fixedID="906" version="1500">
   <color cs="LAB" tints="0.7272,0.739686274509804,0.435764705882353"/>
   <color cs="sRGB" tints="1,0.501960784313725,0.831372549019608"/>
   <color cs="AdobeRGB" tints="0.92156862745098,0.498039215686275,0.815686274509804"/>
  </cs>
  <cs name="PANTONE 907 U" fixedID="907" version="1500">
   <color cs="LAB" tints="0.6723,0.740235294117647,0.390980392156863"/>
   <color cs="sRGB" tints="0.949019607843137,0.443137254901961,0.850980392156863"/>
   <color cs="AdobeRGB" tints="0.843137254901961,0.43921568627451,0.835294117647059"/>
  </cs>
  <cs name="PANTONE 908 U" fixedID="908" version="1500">
   <color cs="LAB" tints="0.662,0.384352941176471,0.362392156862745"/>
   <color cs="sRGB" tints="0,0.701960784313725,0.874509803921569"/>
   <color cs="AdobeRGB" tints="0.368627450980392,0.698039215686274,0.862745098039216"/>
  </cs>
  <cs name="PANTONE 909 U" fixedID="909" version="1500">
   <color cs="LAB" tints="0.8897,0.367176470588235,0.633686274509804"/>
   <color cs="sRGB" tints="0.67843137254902,0.949019607843137,0.611764705882353"/>
   <color cs="AdobeRGB" tints="0.764705882352941,0.945098039215686,0.623529411764706"/>
  </cs>
  <cs name="PANTONE 910 U" fixedID="910" version="1500">
   <color cs="LAB" tints="0.9644,0.480823529411765,0.696588235294118"/>
   <color cs="sRGB" tints="1,0.968627450980392,0.568627450980392"/>
   <color cs="AdobeRGB" tints="1,0.964705882352941,0.588235294117647"/>
  </cs>
  <cs name="PANTONE 911 U" fixedID="911" version="1500">
   <color cs="LAB" tints="0.9117,0.579019607843137,0.640352941176471"/>
   <color cs="sRGB" tints="1,0.843137254901961,0.635294117647059"/>
   <color cs="AdobeRGB" tints="1,0.83921568627451,0.63921568627451"/>
  </cs>
  <cs name="PANTONE 912 U" fixedID="912" version="1500">
   <color cs="LAB" tints="0.8274,0.659254901960784,0.551764705882353"/>
   <color cs="sRGB" tints="1,0.686274509803922,0.72156862745098"/>
   <color cs="AdobeRGB" tints="0.992156862745098,0.682352941176471,0.713725490196078"/>
  </cs>
  <cs name="PANTONE 913 U" fixedID="913" version="1500">
   <color cs="LAB" tints="0.7729,0.694941176470588,0.441921568627451"/>
   <color cs="sRGB" tints="1,0.6,0.866666666666667"/>
   <color cs="AdobeRGB" tints="0.929411764705882,0.596078431372549,0.854901960784314"/>
  </cs>
  <cs name="PANTONE 914 U" fixedID="914" version="1500">
   <color cs="LAB" tints="0.7165,0.710666666666667,0.401098039215686"/>
   <color cs="sRGB" tints="0.964705882352941,0.525490196078431,0.882352941176471"/>
   <color cs="AdobeRGB" tints="0.866666666666667,0.52156862745098,0.866666666666667"/>
  </cs>
  <cs name="PANTONE 915 U" fixedID="915" version="1500">
   <color cs="LAB" tints="0.7104,0.388117647058824,0.373764705882353"/>
   <color cs="sRGB" tints="0.16078431372549,0.752941176470588,0.905882352941176"/>
   <color cs="AdobeRGB" tints="0.443137254901961,0.749019607843137,0.898039215686275"/>
  </cs>
  <cs name="PANTONE 916 U" fixedID="916" version="1500">
   <color cs="LAB" tints="0.9077,0.390509803921569,0.614980392156863"/>
   <color cs="sRGB" tints="0.741176470588235,0.956862745098039,0.666666666666667"/>
   <color cs="AdobeRGB" tints="0.803921568627451,0.956862745098039,0.67843137254902"/>
  </cs>
  <cs name="PANTONE 917 U" fixedID="917" version="1500">
   <color cs="LAB" tints="0.9697,0.477960784313725,0.650627450980392"/>
   <color cs="sRGB" tints="0.996078431372549,0.976470588235294,0.670588235294118"/>
   <color cs="AdobeRGB" tints="0.988235294117647,0.976470588235294,0.682352941176471"/>
  </cs>
  <cs name="PANTONE 918 U" fixedID="918" version="1500">
   <color cs="LAB" tints="0.9368,0.548980392156863,0.602823529411765"/>
   <color cs="sRGB" tints="1,0.894117647058824,0.733333333333333"/>
   <color cs="AdobeRGB" tints="1,0.890196078431373,0.733333333333333"/>
  </cs>
  <cs name="PANTONE 919 U" fixedID="919" version="1500">
   <color cs="LAB" tints="0.8777,0.615411764705882,0.533372549019608"/>
   <color cs="sRGB" tints="1,0.780392156862745,0.807843137254902"/>
   <color cs="AdobeRGB" tints="1,0.776470588235294,0.8"/>
  </cs>
  <cs name="PANTONE 920 U" fixedID="920" version="1500">
   <color cs="LAB" tints="0.8304,0.647490196078431,0.452666666666667"/>
   <color cs="sRGB" tints="1,0.705882352941177,0.909803921568627"/>
   <color cs="AdobeRGB" tints="0.949019607843137,0.701960784313725,0.898039215686275"/>
  </cs>
  <cs name="PANTONE 921 U" fixedID="921" version="1500">
   <color cs="LAB" tints="0.8031,0.653764705882353,0.428"/>
   <color cs="sRGB" tints="0.992156862745098,0.674509803921569,0.925490196078431"/>
   <color cs="AdobeRGB" tints="0.913725490196078,0.666666666666667,0.913725490196078"/>
  </cs>
  <cs name="PANTONE 808 U" fixedID="808" version="1500">
   <color cs="LAB" tints="0.6091,0.300666666666667,0.505098039215686"/>
   <color cs="sRGB" tints="0,0.674509803921569,0.556862745098039"/>
   <color cs="AdobeRGB" tints="0.317647058823529,0.666666666666667,0.556862745098039"/>
  </cs>
  <cs name="PANTONE 809 U" fixedID="809" version="1500">
   <color cs="LAB" tints="0.8951,0.441137254901961,0.802156862745098"/>
   <color cs="sRGB" tints="0.894117647058824,0.909803921568627,0.231372549019608"/>
   <color cs="AdobeRGB" tints="0.894117647058824,0.905882352941176,0.305882352941176"/>
  </cs>
  <cs name="PANTONE 810 U" fixedID="810" version="1500">
   <color cs="LAB" tints="0.9057,0.584745098039216,0.815411764705882"/>
   <color cs="sRGB" tints="1,0.827450980392157,0.235294117647059"/>
   <color cs="AdobeRGB" tints="1,0.819607843137255,0.298039215686275"/>
  </cs>
  <cs name="PANTONE 811 U" fixedID="811" version="1500">
   <color cs="LAB" tints="0.7712,0.743294117647059,0.694"/>
   <color cs="sRGB" tints="1,0.529411764705882,0.403921568627451"/>
   <color cs="AdobeRGB" tints="1,0.525490196078431,0.407843137254902"/>
  </cs>
  <cs name="PANTONE 812 U" fixedID="812" version="1500">
   <color cs="LAB" tints="0.667,0.790352941176471,0.54443137254902"/>
   <color cs="sRGB" tints="1,0.352941176470588,0.576470588235294"/>
   <color cs="AdobeRGB" tints="0.929411764705882,0.352941176470588,0.564705882352941"/>
  </cs>
  <cs name="PANTONE 813 U" fixedID="813" version="1500">
   <color cs="LAB" tints="0.6015,0.798588235294118,0.424705882352941"/>
   <color cs="sRGB" tints="0.96078431372549,0.254901960784314,0.717647058823529"/>
   <color cs="AdobeRGB" tints="0.831372549019608,0.262745098039216,0.701960784313725"/>
  </cs>
  <cs name="PANTONE 814 U" fixedID="814" version="1500">
   <color cs="LAB" tints="0.4712,0.616313725490196,0.304235294117647"/>
   <color cs="sRGB" tints="0.482352941176471,0.368627450980392,0.776470588235294"/>
   <color cs="AdobeRGB" tints="0.450980392156863,0.372549019607843,0.76078431372549"/>
  </cs>
  <cs name="PANTONE 922 U" fixedID="922" version="1500">
   <color cs="LAB" tints="0.6967,0.32321568627451,0.498588235294118"/>
   <color cs="sRGB" tints="0.0980392156862745,0.76078431372549,0.662745098039216"/>
   <color cs="AdobeRGB" tints="0.435294117647059,0.752941176470588,0.658823529411765"/>
  </cs>
  <cs name="PANTONE 923 U" fixedID="923" version="1500">
   <color cs="LAB" tints="0.9376,0.449882352941176,0.73678431372549"/>
   <color cs="sRGB" tints="0.941176470588235,0.952941176470588,0.450980392156863"/>
   <color cs="AdobeRGB" tints="0.941176470588235,0.952941176470588,0.482352941176471"/>
  </cs>
  <cs name="PANTONE 924 U" fixedID="924" version="1500">
   <color cs="LAB" tints="0.9384,0.52756862745098,0.728392156862745"/>
   <color cs="sRGB" tints="1,0.905882352941176,0.47843137254902"/>
   <color cs="AdobeRGB" tints="1,0.901960784313726,0.501960784313725"/>
  </cs>
  <cs name="PANTONE 925 U" fixedID="925" version="1500">
   <color cs="LAB" tints="0.8363,0.662549019607843,0.623019607843137"/>
   <color cs="sRGB" tints="1,0.690196078431373,0.596078431372549"/>
   <color cs="AdobeRGB" tints="1,0.686274509803922,0.596078431372549"/>
  </cs>
  <cs name="PANTONE 926 U" fixedID="926" version="1500">
   <color cs="LAB" tints="0.7562,0.717058823529412,0.499058823529412"/>
   <color cs="sRGB" tints="1,0.556862745098039,0.745098039215686"/>
   <color cs="AdobeRGB" tints="0.952941176470588,0.549019607843137,0.733333333333333"/>
  </cs>
  <cs name="PANTONE 927 U" fixedID="927" version="1500">
   <color cs="LAB" tints="0.7207,0.727490196078431,0.416392156862745"/>
   <color cs="sRGB" tints="1,0.509803921568627,0.858823529411765"/>
   <color cs="AdobeRGB" tints="0.894117647058824,0.505882352941176,0.843137254901961"/>
  </cs>
  <cs name="PANTONE 928 U" fixedID="928" version="1500">
   <color cs="LAB" tints="0.61,0.592352941176471,0.338470588235294"/>
   <color cs="sRGB" tints="0.615686274509804,0.525490196078431,0.870588235294118"/>
   <color cs="AdobeRGB" tints="0.588235294117647,0.52156862745098,0.854901960784314"/>
  </cs>
  <cs name="PANTONE 929 U" fixedID="929" version="1500">
   <color cs="LAB" tints="0.754,0.345764705882353,0.494549019607843"/>
   <color cs="sRGB" tints="0.325490196078431,0.811764705882353,0.729411764705882"/>
   <color cs="AdobeRGB" tints="0.52156862745098,0.807843137254902,0.729411764705882"/>
  </cs>
  <cs name="PANTONE 930 U" fixedID="930" version="1500">
   <color cs="LAB" tints="0.9553,0.459294117647059,0.680666666666667"/>
   <color cs="sRGB" tints="0.956862745098039,0.972549019607843,0.592156862745098"/>
   <color cs="AdobeRGB" tints="0.96078431372549,0.968627450980392,0.607843137254902"/>
  </cs>
  <cs name="PANTONE 931 U" fixedID="931" version="1500">
   <color cs="LAB" tints="0.9494,0.510705882352941,0.686196078431373"/>
   <color cs="sRGB" tints="1,0.933333333333333,0.576470588235294"/>
   <color cs="AdobeRGB" tints="1,0.929411764705882,0.592156862745098"/>
  </cs>
  <cs name="PANTONE 932 U" fixedID="932" version="1500">
   <color cs="LAB" tints="0.8697,0.622156862745098,0.59278431372549"/>
   <color cs="sRGB" tints="1,0.764705882352941,0.686274509803922"/>
   <color cs="AdobeRGB" tints="1,0.76078431372549,0.682352941176471"/>
  </cs>
  <cs name="PANTONE 933 U" fixedID="933" version="1500">
   <color cs="LAB" tints="0.8048,0.671921568627451,0.48678431372549"/>
   <color cs="sRGB" tints="1,0.654901960784314,0.819607843137255"/>
   <color cs="AdobeRGB" tints="0.956862745098039,0.650980392156863,0.807843137254902"/>
  </cs>
  <cs name="PANTONE 934 U" fixedID="934" version="1500">
   <color cs="LAB" tints="0.7759,0.684039215686275,0.426470588235294"/>
   <color cs="sRGB" tints="1,0.615686274509804,0.898039215686275"/>
   <color cs="AdobeRGB" tints="0.913725490196078,0.607843137254902,0.886274509803922"/>
  </cs>
  <cs name="PANTONE 935 U" fixedID="935" version="1500">
   <color cs="LAB" tints="0.6896,0.576235294117647,0.367411764705882"/>
   <color cs="sRGB" tints="0.698039215686274,0.619607843137255,0.905882352941176"/>
   <color cs="AdobeRGB" tints="0.670588235294118,0.611764705882353,0.894117647058824"/>
  </cs>
  <cs name="PANTONE 936 U" fixedID="936" version="1500">
   <color cs="LAB" tints="0.8009,0.370627450980392,0.491411764705882"/>
   <color cs="sRGB" tints="0.466666666666667,0.854901960784314,0.788235294117647"/>
   <color cs="AdobeRGB" tints="0.603921568627451,0.850980392156863,0.788235294117647"/>
  </cs>
  <cs name="PANTONE 937 U" fixedID="937" version="1500">
   <color cs="LAB" tints="0.9633,0.467294117647059,0.642117647058824"/>
   <color cs="sRGB" tints="0.964705882352941,0.976470588235294,0.67843137254902"/>
   <color cs="AdobeRGB" tints="0.968627450980392,0.976470588235294,0.690196078431373"/>
  </cs>
  <cs name="PANTONE 938 U" fixedID="938" version="1500">
   <color cs="LAB" tints="0.9616,0.497803921568627,0.636392156862745"/>
   <color cs="sRGB" tints="1,0.956862745098039,0.690196078431373"/>
   <color cs="AdobeRGB" tints="1,0.952941176470588,0.698039215686274"/>
  </cs>
  <cs name="PANTONE 939 U" fixedID="939" version="1500">
   <color cs="LAB" tints="0.9037,0.58521568627451,0.565882352941177"/>
   <color cs="sRGB" tints="1,0.831372549019608,0.768627450980392"/>
   <color cs="AdobeRGB" tints="1,0.827450980392157,0.768627450980392"/>
  </cs>
  <cs name="PANTONE 940 U" fixedID="940" version="1500">
   <color cs="LAB" tints="0.8533,0.629960784313725,0.485372549019608"/>
   <color cs="sRGB" tints="1,0.745098039215686,0.870588235294118"/>
   <color cs="AdobeRGB" tints="0.968627450980392,0.741176470588235,0.862745098039216"/>
  </cs>
  <cs name="PANTONE 941 U" fixedID="941" version="1500">
   <color cs="LAB" tints="0.819,0.645725490196078,0.438980392156863"/>
   <color cs="sRGB" tints="1,0.698039215686274,0.92156862745098"/>
   <color cs="AdobeRGB" tints="0.929411764705882,0.690196078431373,0.909803921568627"/>
  </cs>
  <cs name="PANTONE 942 U" fixedID="942" version="1500">
   <color cs="LAB" tints="0.7667,0.559490196078431,0.40121568627451"/>
   <color cs="sRGB" tints="0.776470588235294,0.709803921568627,0.929411764705882"/>
   <color cs="AdobeRGB" tints="0.752941176470588,0.705882352941177,0.917647058823529"/>
  </cs>
 </colorspaces>
 <colors>
  <page>
    <color name="PANTONE Yellow 0131 U" cs="PANTONE Yellow 0131 U" tints="1"/>
    <color name="PANTONE Red 0331 U" cs="PANTONE Red 0331 U" tints="1"/>
    <color name="PANTONE Magenta 0521 U" cs="PANTONE Magenta 0521 U" tints="1"/>
    <color name="PANTONE Violet 0631 U" cs="PANTONE Violet 0631 U" tints="1"/>
    <color name="PANTONE Blue 0821 U" cs="PANTONE Blue 0821 U" tints="1"/>
    <color name="PANTONE Green 0921 U" cs="PANTONE Green 0921 U" tints="1"/>
    <color name="PANTONE Black 0961 U" cs="PANTONE Black 0961 U" tints="1"/>
  </page>
  <page>
    <color name="PANTONE 9140 U" cs="PANTONE 9140 U" tints="1"/>
    <color name="PANTONE 9284 U" cs="PANTONE 9284 U" tints="1"/>
    <color name="PANTONE 9324 U" cs="PANTONE 9324 U" tints="1"/>
    <color name="PANTONE 9344 U" cs="PANTONE 9344 U" tints="1"/>
    <color name="PANTONE 9464 U" cs="PANTONE 9464 U" tints="1"/>
    <color name="PANTONE 9524 U" cs="PANTONE 9524 U" tints="1"/>
    <color name="PANTONE 9084 U" cs="PANTONE 9084 U" tints="1"/>
  </page>
  <page>
    <color name="PANTONE 9060 U" cs="PANTONE 9060 U" tints="1"/>
    <color name="PANTONE 9280 U" cs="PANTONE 9280 U" tints="1"/>
    <color name="PANTONE 9320 U" cs="PANTONE 9320 U" tints="1"/>
    <color name="PANTONE 9340 U" cs="PANTONE 9340 U" tints="1"/>
    <color name="PANTONE 9460 U" cs="PANTONE 9460 U" tints="1"/>
    <color name="PANTONE 9520 U" cs="PANTONE 9520 U" tints="1"/>
    <color name="PANTONE 9083 U" cs="PANTONE 9083 U" tints="1"/>
  </page>
  <page>
    <color name="PANTONE 9064 U" cs="PANTONE 9064 U" tints="1"/>
    <color name="PANTONE 9285 U" cs="PANTONE 9285 U" tints="1"/>
    <color name="PANTONE 9061 U" cs="PANTONE 9061 U" tints="1"/>
    <color name="PANTONE 9345 U" cs="PANTONE 9345 U" tints="1"/>
    <color name="PANTONE 9062 U" cs="PANTONE 9062 U" tints="1"/>
    <color name="PANTONE 9063 U" cs="PANTONE 9063 U" tints="1"/>
    <color name="PANTONE 9081 U" cs="PANTONE 9081 U" tints="1"/>
  </page>
  <page>
    <color name="PANTONE 9043 U" cs="PANTONE 9043 U" tints="1"/>
    <color name="PANTONE 9080 U" cs="PANTONE 9080 U" tints="1"/>
    <color name="PANTONE 9100 U" cs="PANTONE 9100 U" tints="1"/>
    <color name="PANTONE 9101 U" cs="PANTONE 9101 U" tints="1"/>
    <color name="PANTONE 9102 U" cs="PANTONE 9102 U" tints="1"/>
    <color name="PANTONE 9103 U" cs="PANTONE 9103 U" tints="1"/>
    <color name="PANTONE 9082 U" cs="PANTONE 9082 U" tints="1"/>
  </page>
  <page>
    <color name="PANTONE 9121 U" cs="PANTONE 9121 U" tints="1"/>
    <color name="PANTONE 9120 U" cs="PANTONE 9120 U" tints="1"/>
    <color name="PANTONE 9141 U" cs="PANTONE 9141 U" tints="1"/>
    <color name="PANTONE 9142 U" cs="PANTONE 9142 U" tints="1"/>
    <color name="PANTONE 9161 U" cs="PANTONE 9161 U" tints="1"/>
    <color name="PANTONE 9143 U" cs="PANTONE 9143 U" tints="1"/>
    <color name="PANTONE 9162 U" cs="PANTONE 9162 U" tints="1"/>
  </page>
  <page>
    <color name="PANTONE 9160 U" cs="PANTONE 9160 U" tints="1"/>
    <color name="PANTONE 9180 U" cs="PANTONE 9180 U" tints="1"/>
    <color name="PANTONE 9181 U" cs="PANTONE 9181 U" tints="1"/>
    <color name="PANTONE 9200 U" cs="PANTONE 9200 U" tints="1"/>
    <color name="PANTONE 9201 U" cs="PANTONE 9201 U" tints="1"/>
    <color name="PANTONE 9220 U" cs="PANTONE 9220 U" tints="1"/>
    <color name="PANTONE 9221 U" cs="PANTONE 9221 U" tints="1"/>
  </page>
  <page>
    <color name="PANTONE 9184 U" cs="PANTONE 9184 U" tints="1"/>
    <color name="PANTONE 9185 U" cs="PANTONE 9185 U" tints="1"/>
    <color name="PANTONE 9202 U" cs="PANTONE 9202 U" tints="1"/>
    <color name="PANTONE 9182 U" cs="PANTONE 9182 U" tints="1"/>
    <color name="PANTONE 9183 U" cs="PANTONE 9183 U" tints="1"/>
    <color name="PANTONE 9203 U" cs="PANTONE 9203 U" tints="1"/>
    <color name="PANTONE 9186 U" cs="PANTONE 9186 U" tints="1"/>
  </page>
  <page>
    <color name="PANTONE 9224 U" cs="PANTONE 9224 U" tints="1"/>
    <color name="PANTONE 9225 U" cs="PANTONE 9225 U" tints="1"/>
    <color name="PANTONE 9226 U" cs="PANTONE 9226 U" tints="1"/>
    <color name="PANTONE 9222 U" cs="PANTONE 9222 U" tints="1"/>
    <color name="PANTONE 9223 U" cs="PANTONE 9223 U" tints="1"/>
    <color name="PANTONE 9242 U" cs="PANTONE 9242 U" tints="1"/>
    <color name="PANTONE 9243 U" cs="PANTONE 9243 U" tints="1"/>
  </page>
  <page>
    <color name="PANTONE 9244 U" cs="PANTONE 9244 U" tints="1"/>
    <color name="PANTONE 9240 U" cs="PANTONE 9240 U" tints="1"/>
    <color name="PANTONE 9260 U" cs="PANTONE 9260 U" tints="1"/>
    <color name="PANTONE 9241 U" cs="PANTONE 9241 U" tints="1"/>
    <color name="PANTONE 9261 U" cs="PANTONE 9261 U" tints="1"/>
    <color name="PANTONE 9262 U" cs="PANTONE 9262 U" tints="1"/>
    <color name="PANTONE 9263 U" cs="PANTONE 9263 U" tints="1"/>
  </page>
  <page>
    <color name="PANTONE 9286 U" cs="PANTONE 9286 U" tints="1"/>
    <color name="PANTONE 9281 U" cs="PANTONE 9281 U" tints="1"/>
    <color name="PANTONE 9300 U" cs="PANTONE 9300 U" tints="1"/>
    <color name="PANTONE 9282 U" cs="PANTONE 9282 U" tints="1"/>
    <color name="PANTONE 9301 U" cs="PANTONE 9301 U" tints="1"/>
    <color name="PANTONE 9321 U" cs="PANTONE 9321 U" tints="1"/>
    <color name="PANTONE 9302 U" cs="PANTONE 9302 U" tints="1"/>
  </page>
  <page>
    <color name="PANTONE 9021 U" cs="PANTONE 9021 U" tints="1"/>
    <color name="PANTONE 9022 U" cs="PANTONE 9022 U" tints="1"/>
    <color name="PANTONE 9023 U" cs="PANTONE 9023 U" tints="1"/>
    <color name="PANTONE 9283 U" cs="PANTONE 9283 U" tints="1"/>
    <color name="PANTONE 9303 U" cs="PANTONE 9303 U" tints="1"/>
    <color name="PANTONE 9322 U" cs="PANTONE 9322 U" tints="1"/>
    <color name="PANTONE 9323 U" cs="PANTONE 9323 U" tints="1"/>
  </page>
  <page>
    <color name="PANTONE 9360 U" cs="PANTONE 9360 U" tints="1"/>
    <color name="PANTONE 9341 U" cs="PANTONE 9341 U" tints="1"/>
    <color name="PANTONE 9342 U" cs="PANTONE 9342 U" tints="1"/>
    <color name="PANTONE 9343 U" cs="PANTONE 9343 U" tints="1"/>
    <color name="PANTONE 9361 U" cs="PANTONE 9361 U" tints="1"/>
    <color name="PANTONE 9362 U" cs="PANTONE 9362 U" tints="1"/>
    <color name="PANTONE 9363 U" cs="PANTONE 9363 U" tints="1"/>
  </page>
  <page>
    <color name="PANTONE 9380 U" cs="PANTONE 9380 U" tints="1"/>
    <color name="PANTONE 9384 U" cs="PANTONE 9384 U" tints="1"/>
    <color name="PANTONE 9381 U" cs="PANTONE 9381 U" tints="1"/>
    <color name="PANTONE 9382 U" cs="PANTONE 9382 U" tints="1"/>
    <color name="PANTONE 9383 U" cs="PANTONE 9383 U" tints="1"/>
    <color name="PANTONE 9385 U" cs="PANTONE 9385 U" tints="1"/>
    <color name="PANTONE 9403 U" cs="PANTONE 9403 U" tints="1"/>
  </page>
  <page>
    <color name="PANTONE 9400 U" cs="PANTONE 9400 U" tints="1"/>
    <color name="PANTONE 9401 U" cs="PANTONE 9401 U" tints="1"/>
    <color name="PANTONE 9402 U" cs="PANTONE 9402 U" tints="1"/>
    <color name="PANTONE 9420 U" cs="PANTONE 9420 U" tints="1"/>
    <color name="PANTONE 9421 U" cs="PANTONE 9421 U" tints="1"/>
    <color name="PANTONE 9422 U" cs="PANTONE 9422 U" tints="1"/>
    <color name="PANTONE 9423 U" cs="PANTONE 9423 U" tints="1"/>
  </page>
  <page>
    <color name="PANTONE 9424 U" cs="PANTONE 9424 U" tints="1"/>
    <color name="PANTONE 9440 U" cs="PANTONE 9440 U" tints="1"/>
    <color name="PANTONE 9441 U" cs="PANTONE 9441 U" tints="1"/>
    <color name="PANTONE 9442 U" cs="PANTONE 9442 U" tints="1"/>
    <color name="PANTONE 9461 U" cs="PANTONE 9461 U" tints="1"/>
    <color name="PANTONE 9462 U" cs="PANTONE 9462 U" tints="1"/>
    <color name="PANTONE 9443 U" cs="PANTONE 9443 U" tints="1"/>
  </page>
  <page>
    <color name="PANTONE 9480 U" cs="PANTONE 9480 U" tints="1"/>
    <color name="PANTONE 9481 U" cs="PANTONE 9481 U" tints="1"/>
    <color name="PANTONE 9500 U" cs="PANTONE 9500 U" tints="1"/>
    <color name="PANTONE 9482 U" cs="PANTONE 9482 U" tints="1"/>
    <color name="PANTONE 9501 U" cs="PANTONE 9501 U" tints="1"/>
    <color name="PANTONE 9483 U" cs="PANTONE 9483 U" tints="1"/>
    <color name="PANTONE 9463 U" cs="PANTONE 9463 U" tints="1"/>
  </page>
  <page>
    <color name="PANTONE 9042 U" cs="PANTONE 9042 U" tints="1"/>
    <color name="PANTONE 9041 U" cs="PANTONE 9041 U" tints="1"/>
    <color name="PANTONE 9040 U" cs="PANTONE 9040 U" tints="1"/>
    <color name="PANTONE 9044 U" cs="PANTONE 9044 U" tints="1"/>
    <color name="PANTONE 9045 U" cs="PANTONE 9045 U" tints="1"/>
    <color name="PANTONE 9503 U" cs="PANTONE 9503 U" tints="1"/>
    <color name="PANTONE 9504 U" cs="PANTONE 9504 U" tints="1"/>
  </page>
  <page>
    <color name="PANTONE 9525 U" cs="PANTONE 9525 U" tints="1"/>
    <color name="PANTONE 9540 U" cs="PANTONE 9540 U" tints="1"/>
    <color name="PANTONE 9541 U" cs="PANTONE 9541 U" tints="1"/>
    <color name="PANTONE 9521 U" cs="PANTONE 9521 U" tints="1"/>
    <color name="PANTONE 9522 U" cs="PANTONE 9522 U" tints="1"/>
    <color name="PANTONE 9523 U" cs="PANTONE 9523 U" tints="1"/>
    <color name="PANTONE 9502 U" cs="PANTONE 9502 U" tints="1"/>
  </page>
  <page>
    <color name="PANTONE 9544 U" cs="PANTONE 9544 U" tints="1"/>
    <color name="PANTONE 9560 U" cs="PANTONE 9560 U" tints="1"/>
    <color name="PANTONE 9561 U" cs="PANTONE 9561 U" tints="1"/>
    <color name="PANTONE 9562 U" cs="PANTONE 9562 U" tints="1"/>
    <color name="PANTONE 9563 U" cs="PANTONE 9563 U" tints="1"/>
    <color name="PANTONE 9542 U" cs="PANTONE 9542 U" tints="1"/>
    <color name="PANTONE 9543 U" cs="PANTONE 9543 U" tints="1"/>
  </page>
  <page>
    <color name="PANTONE 9020 U" cs="PANTONE 9020 U" tints="1"/>
    <color name="PANTONE 9600 U" cs="PANTONE 9600 U" tints="1"/>
    <color name="PANTONE 9601 U" cs="PANTONE 9601 U" tints="1"/>
    <color name="PANTONE 9122 U" cs="PANTONE 9122 U" tints="1"/>
    <color name="PANTONE 9602 U" cs="PANTONE 9602 U" tints="1"/>
    <color name="PANTONE 9603 U" cs="PANTONE 9603 U" tints="1"/>
    <color name="PANTONE 9123 U" cs="PANTONE 9123 U" tints="1"/>
  </page>
  <page>
    <color name="PANTONE 9580 U" cs="PANTONE 9580 U" tints="1"/>
    <color name="PANTONE 9581 U" cs="PANTONE 9581 U" tints="1"/>
    <color name="PANTONE 9584 U" cs="PANTONE 9584 U" tints="1"/>
    <color name="PANTONE 9582 U" cs="PANTONE 9582 U" tints="1"/>
    <color name="PANTONE 9583 U" cs="PANTONE 9583 U" tints="1"/>
    <color name="PANTONE 9585 U" cs="PANTONE 9585 U" tints="1"/>
    <color name="PANTONE 9163 U" cs="PANTONE 9163 U" tints="1"/>
  </page>
  <page>
    <color name="PANTONE 801 U" cs="PANTONE 801 U" tints="1"/>
    <color name="PANTONE 802 U" cs="PANTONE 802 U" tints="1"/>
    <color name="PANTONE 803 U" cs="PANTONE 803 U" tints="1"/>
    <color name="PANTONE 804 U" cs="PANTONE 804 U" tints="1"/>
    <color name="PANTONE 805 U" cs="PANTONE 805 U" tints="1"/>
    <color name="PANTONE 806 U" cs="PANTONE 806 U" tints="1"/>
    <color name="PANTONE 807 U" cs="PANTONE 807 U" tints="1"/>
  </page>
  <page>
    <color name="PANTONE 901 U" cs="PANTONE 901 U" tints="1"/>
    <color name="PANTONE 902 U" cs="PANTONE 902 U" tints="1"/>
    <color name="PANTONE 903 U" cs="PANTONE 903 U" tints="1"/>
    <color name="PANTONE 904 U" cs="PANTONE 904 U" tints="1"/>
    <color name="PANTONE 905 U" cs="PANTONE 905 U" tints="1"/>
    <color name="PANTONE 906 U" cs="PANTONE 906 U" tints="1"/>
    <color name="PANTONE 907 U" cs="PANTONE 907 U" tints="1"/>
  </page>
  <page>
    <color name="PANTONE 908 U" cs="PANTONE 908 U" tints="1"/>
    <color name="PANTONE 909 U" cs="PANTONE 909 U" tints="1"/>
    <color name="PANTONE 910 U" cs="PANTONE 910 U" tints="1"/>
    <color name="PANTONE 911 U" cs="PANTONE 911 U" tints="1"/>
    <color name="PANTONE 912 U" cs="PANTONE 912 U" tints="1"/>
    <color name="PANTONE 913 U" cs="PANTONE 913 U" tints="1"/>
    <color name="PANTONE 914 U" cs="PANTONE 914 U" tints="1"/>
  </page>
  <page>
    <color name="PANTONE 915 U" cs="PANTONE 915 U" tints="1"/>
    <color name="PANTONE 916 U" cs="PANTONE 916 U" tints="1"/>
    <color name="PANTONE 917 U" cs="PANTONE 917 U" tints="1"/>
    <color name="PANTONE 918 U" cs="PANTONE 918 U" tints="1"/>
    <color name="PANTONE 919 U" cs="PANTONE 919 U" tints="1"/>
    <color name="PANTONE 920 U" cs="PANTONE 920 U" tints="1"/>
    <color name="PANTONE 921 U" cs="PANTONE 921 U" tints="1"/>
  </page>
  <page>
    <color name="PANTONE 808 U" cs="PANTONE 808 U" tints="1"/>
    <color name="PANTONE 809 U" cs="PANTONE 809 U" tints="1"/>
    <color name="PANTONE 810 U" cs="PANTONE 810 U" tints="1"/>
    <color name="PANTONE 811 U" cs="PANTONE 811 U" tints="1"/>
    <color name="PANTONE 812 U" cs="PANTONE 812 U" tints="1"/>
    <color name="PANTONE 813 U" cs="PANTONE 813 U" tints="1"/>
    <color name="PANTONE 814 U" cs="PANTONE 814 U" tints="1"/>
  </page>
  <page>
    <color name="PANTONE 922 U" cs="PANTONE 922 U" tints="1"/>
    <color name="PANTONE 923 U" cs="PANTONE 923 U" tints="1"/>
    <color name="PANTONE 924 U" cs="PANTONE 924 U" tints="1"/>
    <color name="PANTONE 925 U" cs="PANTONE 925 U" tints="1"/>
    <color name="PANTONE 926 U" cs="PANTONE 926 U" tints="1"/>
    <color name="PANTONE 927 U" cs="PANTONE 927 U" tints="1"/>
    <color name="PANTONE 928 U" cs="PANTONE 928 U" tints="1"/>
  </page>
  <page>
    <color name="PANTONE 929 U" cs="PANTONE 929 U" tints="1"/>
    <color name="PANTONE 930 U" cs="PANTONE 930 U" tints="1"/>
    <color name="PANTONE 931 U" cs="PANTONE 931 U" tints="1"/>
    <color name="PANTONE 932 U" cs="PANTONE 932 U" tints="1"/>
    <color name="PANTONE 933 U" cs="PANTONE 933 U" tints="1"/>
    <color name="PANTONE 934 U" cs="PANTONE 934 U" tints="1"/>
    <color name="PANTONE 935 U" cs="PANTONE 935 U" tints="1"/>
  </page>
  <page>
    <color name="PANTONE 936 U" cs="PANTONE 936 U" tints="1"/>
    <color name="PANTONE 937 U" cs="PANTONE 937 U" tints="1"/>
    <color name="PANTONE 938 U" cs="PANTONE 938 U" tints="1"/>
    <color name="PANTONE 939 U" cs="PANTONE 939 U" tints="1"/>
    <color name="PANTONE 940 U" cs="PANTONE 940 U" tints="1"/>
    <color name="PANTONE 941 U" cs="PANTONE 941 U" tints="1"/>
    <color name="PANTONE 942 U" cs="PANTONE 942 U" tints="1"/>
  </page>
 </colors>
</palette>
